{
    "meta": {
        "file_name": "262.json",
        "id_bd": 262,
        "author": "Isbedy Stiawan ZS",
        "title": "Perjalanan pelaut",
        "genre": "стихотворение",
        "year": 1987,
        "num_lines": 12,
        "rhyme": "Спорадическая",
        "syllables": [
            14,
            15,
            14,
            12,
            8,
            16,
            11,
            14,
            11,
            16,
            15,
            14
        ],
        "strofy": [
            12
        ]
    },
    "poem": {
        "text": "{karena laut mengajarkan rahasia badai\r\naku pun setia berlayar. dari pulau asing\r\nke pulau asing aku tebarkan benih pelaut\r\ndan lalu meninggalkan ratusan rumah\r\nyang memendam kesepian\r\nrumah hanya istirah bagi kejenuhan kapal. oh,\r\nlaut yang terapit oleh pulau-pulau\r\ndi mana tubuhku sesekali dibaringkan?\r\ndari pulau asing ke pulau asing\r\naku pahami rahasia badai, aku tebarkan\r\nbenih pelaut. sementara pada kedalaman laut\r\nkubur mengajarkan rahasia paling akhir}",
        "strof": [
            {
                "strof": "karena laut mengajarkan rahasia badai\r\naku pun setia berlayar. dari pulau asing\r\nke pulau asing aku tebarkan benih pelaut\r\ndan lalu meninggalkan ratusan rumah\r\nyang memendam kesepian\r\nrumah hanya istirah bagi kejenuhan kapal. oh,\r\nlaut yang terapit oleh pulau-pulau\r\ndi mana tubuhku sesekali dibaringkan?\r\ndari pulau asing ke pulau asing\r\naku pahami rahasia badai, aku tebarkan\r\nbenih pelaut. sementara pada kedalaman laut\r\nkubur mengajarkan rahasia paling akhir",
                "lines": [
                    {
                        "line": "karena laut mengajarkan rahasia badai",
                        "words": [
                            {
                                "wf": "karena",
                                "wtype": "word",
                                "ana": {
                                    "root": "karena",
                                    "pos": "p",
                                    "form": "karena"
                                }
                            },
                            {
                                "wf": "laut",
                                "wtype": "word",
                                "ana": {
                                    "root": "laut",
                                    "pos": "n",
                                    "form": "laut"
                                }
                            },
                            {
                                "wf": "mengajarkan",
                                "wtype": "word",
                                "ana": {
                                    "root": "ajar",
                                    "pos": "v",
                                    "form": "meN-ajar-kan"
                                }
                            },
                            {
                                "wf": "rahasia",
                                "wtype": "word",
                                "ana": {
                                    "root": "rahasia",
                                    "pos": "n|a",
                                    "form": "rahasia"
                                }
                            },
                            {
                                "wf": "badai",
                                "wtype": "word",
                                "ana": {
                                    "root": "badai",
                                    "pos": "n",
                                    "form": "badai"
                                }
                            }
                        ],
                        "syllables": 14
                    },
                    {
                        "line": "aku pun setia berlayar. dari pulau asing",
                        "words": [
                            {
                                "wf": "aku",
                                "wtype": "word",
                                "ana": {
                                    "root": "aku",
                                    "pos": "pron",
                                    "form": "aku"
                                }
                            },
                            {
                                "wf": "pun",
                                "wtype": "word",
                                "ana": {
                                    "root": "pun",
                                    "pos": "p",
                                    "form": "pun"
                                }
                            },
                            {
                                "wf": "setia",
                                "wtype": "word",
                                "ana": {
                                    "root": "setia",
                                    "pos": "a",
                                    "form": "setia"
                                }
                            },
                            {
                                "wf": "berlayar",
                                "wtype": "word",
                                "ana": {
                                    "root": "layar",
                                    "pos": "v",
                                    "form": "berlayar"
                                }
                            },
                            {
                                "wf": ". ",
                                "wtype": "punct"
                            },
                            {
                                "wf": "dari",
                                "wtype": "word",
                                "ana": {
                                    "root": "dari",
                                    "pos": "p",
                                    "form": "dari"
                                }
                            },
                            {
                                "wf": "pulau",
                                "wtype": "word",
                                "ana": {
                                    "root": "pulau",
                                    "pos": "n",
                                    "form": "pulau"
                                }
                            },
                            {
                                "wf": "asing",
                                "wtype": "word",
                                "ana": {
                                    "root": "asing",
                                    "pos": "a",
                                    "form": "asing"
                                }
                            }
                        ],
                        "syllables": 15
                    },
                    {
                        "line": "ke pulau asing aku tebarkan benih pelaut",
                        "words": [
                            {
                                "wf": "ke",
                                "wtype": "word",
                                "ana": {
                                    "root": "ke",
                                    "pos": "p",
                                    "form": "ke"
                                }
                            },
                            {
                                "wf": "pulau",
                                "wtype": "word",
                                "ana": {
                                    "root": "pulau",
                                    "pos": "n",
                                    "form": "pulau"
                                }
                            },
                            {
                                "wf": "asing",
                                "wtype": "word",
                                "ana": {
                                    "root": "asing",
                                    "pos": "a",
                                    "form": "asing"
                                }
                            },
                            {
                                "wf": "aku",
                                "wtype": "word",
                                "ana": {
                                    "root": "aku",
                                    "pos": "pron",
                                    "form": "aku"
                                }
                            },
                            {
                                "wf": "tebarkan",
                                "wtype": "word",
                                "ana": {
                                    "root": "tebarkan",
                                    "pos": "v",
                                    "form": "tebarkan"
                                }
                            },
                            {
                                "wf": "benih",
                                "wtype": "word",
                                "ana": {
                                    "root": "benih",
                                    "pos": "n",
                                    "form": "benih"
                                }
                            },
                            {
                                "wf": "pelaut",
                                "wtype": "word",
                                "ana": {
                                    "root": "laut",
                                    "pos": "n",
                                    "form": "peN-laut"
                                }
                            }
                        ],
                        "syllables": 14
                    },
                    {
                        "line": "dan lalu meninggalkan ratusan rumah",
                        "words": [
                            {
                                "wf": "dan",
                                "wtype": "word",
                                "ana": {
                                    "root": "dan",
                                    "pos": "p",
                                    "form": "dan"
                                }
                            },
                            {
                                "wf": "lalu",
                                "wtype": "word",
                                "ana": {
                                    "root": "lalu",
                                    "pos": "adv",
                                    "form": "lalu"
                                }
                            },
                            {
                                "wf": "meninggalkan",
                                "wtype": "word",
                                "ana": {
                                    "root": "tinggal",
                                    "pos": "v",
                                    "form": "meN-tinggal-kan"
                                }
                            },
                            {
                                "wf": "ratusan",
                                "wtype": "word",
                                "ana": {
                                    "root": "ratus",
                                    "pos": "num",
                                    "form": "ratus-an"
                                }
                            },
                            {
                                "wf": "rumah",
                                "wtype": "word",
                                "ana": {
                                    "root": "rumah",
                                    "pos": "n",
                                    "form": "rumah"
                                }
                            }
                        ],
                        "syllables": 12
                    },
                    {
                        "line": "yang memendam kesepian",
                        "words": [
                            {
                                "wf": "yang",
                                "wtype": "word",
                                "ana": {
                                    "root": "yang",
                                    "pos": "a|v|n",
                                    "form": "yang"
                                }
                            },
                            {
                                "wf": "memendam",
                                "wtype": "word",
                                "ana": {
                                    "root": "pendam",
                                    "pos": "v",
                                    "form": "meN-pendam"
                                }
                            },
                            {
                                "wf": "kesepian",
                                "wtype": "word",
                                "ana": {
                                    "root": "sepi",
                                    "pos": "n",
                                    "form": "ke-sepi-an"
                                }
                            }
                        ],
                        "syllables": 8
                    },
                    {
                        "line": "rumah hanya istirah bagi kejenuhan kapal. oh,",
                        "words": [
                            {
                                "wf": "rumah",
                                "wtype": "word",
                                "ana": {
                                    "root": "rumah",
                                    "pos": "n",
                                    "form": "rumah"
                                }
                            },
                            {
                                "wf": "hanya",
                                "wtype": "word",
                                "ana": {
                                    "root": "hanya",
                                    "pos": "adv",
                                    "form": "hanya"
                                }
                            },
                            {
                                "wf": "istirah",
                                "wtype": "word",
                                "ana": {
                                    "root": "istirah",
                                    "pos": "?",
                                    "form": "istirah"
                                }
                            },
                            {
                                "wf": "bagi",
                                "wtype": "word",
                                "ana": {
                                    "root": "bagi",
                                    "pos": "p",
                                    "form": "bagi"
                                }
                            },
                            {
                                "wf": "kejenuhan",
                                "wtype": "word",
                                "ana": {
                                    "root": "kejenuhan",
                                    "pos": "n|a",
                                    "form": "kejenuhan"
                                }
                            },
                            {
                                "wf": "kapal",
                                "wtype": "word",
                                "ana": {
                                    "root": "kapal",
                                    "pos": "n",
                                    "form": "kapal"
                                }
                            },
                            {
                                "wf": ". ",
                                "wtype": "punct"
                            },
                            {
                                "wf": "oh",
                                "wtype": "word",
                                "ana": {
                                    "root": "oh",
                                    "pos": "n",
                                    "form": "oh"
                                }
                            },
                            {
                                "wf": ",",
                                "wtype": "punct"
                            }
                        ],
                        "syllables": 16
                    },
                    {
                        "line": "laut yang terapit oleh pulau-pulau",
                        "words": [
                            {
                                "wf": "laut",
                                "wtype": "word",
                                "ana": {
                                    "root": "laut",
                                    "pos": "n",
                                    "form": "laut"
                                }
                            },
                            {
                                "wf": "yang",
                                "wtype": "word",
                                "ana": {
                                    "root": "yang",
                                    "pos": "a|v|n",
                                    "form": "yang"
                                }
                            },
                            {
                                "wf": "terapit",
                                "wtype": "word",
                                "ana": {
                                    "root": "apit",
                                    "pos": "n",
                                    "form": "ter-apit"
                                }
                            },
                            {
                                "wf": "oleh",
                                "wtype": "word",
                                "ana": {
                                    "root": "oleh",
                                    "pos": "",
                                    "form": "oleh"
                                }
                            },
                            {
                                "wf": "pulau-pulau",
                                "wtype": "word",
                                "ana": {
                                    "root": "pulau",
                                    "pos": "n",
                                    "form": "pulau-pulau"
                                }
                            }
                        ],
                        "syllables": 11
                    },
                    {
                        "line": "di mana tubuhku sesekali dibaringkan?",
                        "words": [
                            {
                                "wf": "di",
                                "wtype": "word",
                                "ana": {
                                    "root": "di",
                                    "pos": "p",
                                    "form": "di"
                                }
                            },
                            {
                                "wf": "mana",
                                "wtype": "word",
                                "ana": {
                                    "root": "mana",
                                    "pos": "pron",
                                    "form": "mana"
                                }
                            },
                            {
                                "wf": "tubuhku",
                                "wtype": "word",
                                "ana": {
                                    "root": "tubuh",
                                    "pos": "n",
                                    "form": "tubuh-ku"
                                }
                            },
                            {
                                "wf": "sesekali",
                                "wtype": "word",
                                "ana": {
                                    "root": "kali",
                                    "pos": "adv",
                                    "form": "se-se-kali"
                                }
                            },
                            {
                                "wf": "dibaringkan",
                                "wtype": "word",
                                "ana": {
                                    "root": "dibaringkan",
                                    "pos": "v",
                                    "form": "dibaringkan"
                                }
                            },
                            {
                                "wf": "?",
                                "wtype": "punct"
                            }
                        ],
                        "syllables": 14
                    },
                    {
                        "line": "dari pulau asing ke pulau asing",
                        "words": [
                            {
                                "wf": "dari",
                                "wtype": "word",
                                "ana": {
                                    "root": "dari",
                                    "pos": "p",
                                    "form": "dari"
                                }
                            },
                            {
                                "wf": "pulau",
                                "wtype": "word",
                                "ana": {
                                    "root": "pulau",
                                    "pos": "n",
                                    "form": "pulau"
                                }
                            },
                            {
                                "wf": "asing",
                                "wtype": "word",
                                "ana": {
                                    "root": "asing",
                                    "pos": "a",
                                    "form": "asing"
                                }
                            },
                            {
                                "wf": "ke",
                                "wtype": "word",
                                "ana": {
                                    "root": "ke",
                                    "pos": "p",
                                    "form": "ke"
                                }
                            },
                            {
                                "wf": "pulau",
                                "wtype": "word",
                                "ana": {
                                    "root": "pulau",
                                    "pos": "n",
                                    "form": "pulau"
                                }
                            },
                            {
                                "wf": "asing",
                                "wtype": "word",
                                "ana": {
                                    "root": "asing",
                                    "pos": "a",
                                    "form": "asing"
                                }
                            }
                        ],
                        "syllables": 11
                    },
                    {
                        "line": "aku pahami rahasia badai, aku tebarkan",
                        "words": [
                            {
                                "wf": "aku",
                                "wtype": "word",
                                "ana": {
                                    "root": "aku",
                                    "pos": "pron",
                                    "form": "aku"
                                }
                            },
                            {
                                "wf": "pahami",
                                "wtype": "word",
                                "ana": {
                                    "root": "pahami",
                                    "pos": "v",
                                    "form": "pahami"
                                }
                            },
                            {
                                "wf": "rahasia",
                                "wtype": "word",
                                "ana": {
                                    "root": "rahasia",
                                    "pos": "n|a",
                                    "form": "rahasia"
                                }
                            },
                            {
                                "wf": "badai",
                                "wtype": "word",
                                "ana": {
                                    "root": "badai",
                                    "pos": "n",
                                    "form": "badai"
                                }
                            },
                            {
                                "wf": ", ",
                                "wtype": "punct"
                            },
                            {
                                "wf": "aku",
                                "wtype": "word",
                                "ana": {
                                    "root": "aku",
                                    "pos": "pron",
                                    "form": "aku"
                                }
                            },
                            {
                                "wf": "tebarkan",
                                "wtype": "word",
                                "ana": {
                                    "root": "tebarkan",
                                    "pos": "v",
                                    "form": "tebarkan"
                                }
                            }
                        ],
                        "syllables": 16
                    },
                    {
                        "line": "benih pelaut. sementara pada kedalaman laut",
                        "words": [
                            {
                                "wf": "benih",
                                "wtype": "word",
                                "ana": {
                                    "root": "benih",
                                    "pos": "n",
                                    "form": "benih"
                                }
                            },
                            {
                                "wf": "pelaut",
                                "wtype": "word",
                                "ana": {
                                    "root": "laut",
                                    "pos": "n",
                                    "form": "peN-laut"
                                }
                            },
                            {
                                "wf": ". ",
                                "wtype": "punct"
                            },
                            {
                                "wf": "sementara",
                                "wtype": "word",
                                "ana": {
                                    "root": "sementara",
                                    "pos": "p|n|num",
                                    "form": "sementara"
                                }
                            },
                            {
                                "wf": "pada",
                                "wtype": "word",
                                "ana": {
                                    "root": "pada",
                                    "pos": "p",
                                    "form": "pada"
                                }
                            },
                            {
                                "wf": "kedalaman",
                                "wtype": "word",
                                "ana": {
                                    "root": "dalam",
                                    "pos": "n|a",
                                    "form": "ke-dalam-an"
                                }
                            },
                            {
                                "wf": "laut",
                                "wtype": "word",
                                "ana": {
                                    "root": "laut",
                                    "pos": "n",
                                    "form": "laut"
                                }
                            }
                        ],
                        "syllables": 15
                    },
                    {
                        "line": "kubur mengajarkan rahasia paling akhir",
                        "words": [
                            {
                                "wf": "kubur",
                                "wtype": "word",
                                "ana": {
                                    "root": "kubur",
                                    "pos": "n",
                                    "form": "kubur"
                                }
                            },
                            {
                                "wf": "mengajarkan",
                                "wtype": "word",
                                "ana": {
                                    "root": "ajar",
                                    "pos": "v",
                                    "form": "meN-ajar-kan"
                                }
                            },
                            {
                                "wf": "rahasia",
                                "wtype": "word",
                                "ana": {
                                    "root": "rahasia",
                                    "pos": "n|a",
                                    "form": "rahasia"
                                }
                            },
                            {
                                "wf": "paling",
                                "wtype": "word",
                                "ana": {
                                    "root": "paling",
                                    "pos": "v",
                                    "form": "paling"
                                }
                            },
                            {
                                "wf": "akhir",
                                "wtype": "word",
                                "ana": {
                                    "root": "akhir",
                                    "pos": "n",
                                    "form": "akhir"
                                }
                            }
                        ],
                        "syllables": 14
                    }
                ],
                "num_lines": 12
            }
        ]
    }
}