{
    "meta": {
        "file_name": "434.json",
        "id_bd": 434,
        "author": "Muhammad Yamin",
        "title": "Gubahan",
        "genre": "стихотворение",
        "year": "---",
        "num_lines": 14,
        "rhyme": "Есть",
        "syllables": [
            10,
            11,
            13,
            10,
            10,
            11,
            11,
            12,
            11,
            11,
            13,
            7,
            12,
            11
        ],
        "strofy": [
            14
        ]
    },
    "poem": {
        "text": "{Beta bertanam bunga cempaka\r\nDi tengah halaman tanah pusaka,\r\nSupaya selamanya, segenap ketika\r\nHarum berbau, semerbak belaka.\r\nBeta berahu bersuka raya\r\nSekiranya bunga puspa mulia\r\nDipetik handaiku, muda usia\r\nDijadikan karangan, nan permai kaya\r\nSemenjak kuntuman, kecil semula\r\nBeta berniat membuat pahala,\r\nMenjadikan perhiasan, atas kepala.\r\nO  Cempaka, wangi baunya\r\nMari kupetik seberapa adanya\r\nBiar kugubah waktu la’i muda.}",
        "strof": [
            {
                "strof": "Beta bertanam bunga cempaka\r\nDi tengah halaman tanah pusaka,\r\nSupaya selamanya, segenap ketika\r\nHarum berbau, semerbak belaka.\r\nBeta berahu bersuka raya\r\nSekiranya bunga puspa mulia\r\nDipetik handaiku, muda usia\r\nDijadikan karangan, nan permai kaya\r\nSemenjak kuntuman, kecil semula\r\nBeta berniat membuat pahala,\r\nMenjadikan perhiasan, atas kepala.\r\nO  Cempaka, wangi baunya\r\nMari kupetik seberapa adanya\r\nBiar kugubah waktu la’i muda.",
                "lines": [
                    {
                        "line": "Beta bertanam bunga cempaka",
                        "words": [
                            {
                                "wf": "Beta",
                                "wtype": "word",
                                "ana": {
                                    "root": "beta",
                                    "pos": "v",
                                    "form": "beta"
                                }
                            },
                            {
                                "wf": "bertanam",
                                "wtype": "word",
                                "ana": {
                                    "root": "tanam",
                                    "pos": "v",
                                    "form": "ber-tanam"
                                }
                            },
                            {
                                "wf": "bunga",
                                "wtype": "word",
                                "ana": {
                                    "root": "bunga",
                                    "pos": "n",
                                    "form": "bunga"
                                }
                            },
                            {
                                "wf": "cempaka",
                                "wtype": "word",
                                "ana": {
                                    "root": "cempaka",
                                    "pos": "n",
                                    "form": "cempaka"
                                }
                            }
                        ],
                        "syllables": 10
                    },
                    {
                        "line": "Di tengah halaman tanah pusaka,",
                        "words": [
                            {
                                "wf": "Di",
                                "wtype": "word",
                                "ana": {
                                    "root": "di",
                                    "pos": "p",
                                    "form": "di"
                                }
                            },
                            {
                                "wf": "tengah",
                                "wtype": "word",
                                "ana": {
                                    "root": "tengah",
                                    "pos": "n",
                                    "form": "tengah"
                                }
                            },
                            {
                                "wf": "halaman",
                                "wtype": "word",
                                "ana": {
                                    "root": "halaman",
                                    "pos": "n",
                                    "form": "halaman"
                                }
                            },
                            {
                                "wf": "tanah",
                                "wtype": "word",
                                "ana": {
                                    "root": "tanah",
                                    "pos": "n",
                                    "form": "tanah"
                                }
                            },
                            {
                                "wf": "pusaka",
                                "wtype": "word",
                                "ana": {
                                    "root": "pusaka",
                                    "pos": "n",
                                    "form": "pusaka"
                                }
                            },
                            {
                                "wf": ",",
                                "wtype": "punct"
                            }
                        ],
                        "syllables": 11
                    },
                    {
                        "line": "Supaya selamanya, segenap ketika",
                        "words": [
                            {
                                "wf": "Supaya",
                                "wtype": "word",
                                "ana": {
                                    "root": "supaya",
                                    "pos": "p",
                                    "form": "supaya"
                                }
                            },
                            {
                                "wf": "selamanya",
                                "wtype": "word",
                                "ana": {
                                    "root": "lama",
                                    "pos": "adv",
                                    "form": "se-lama-nya"
                                }
                            },
                            {
                                "wf": ", ",
                                "wtype": "punct"
                            },
                            {
                                "wf": "segenap",
                                "wtype": "word",
                                "ana": {
                                    "root": "genap",
                                    "pos": "num",
                                    "form": "se-genap"
                                }
                            },
                            {
                                "wf": "ketika",
                                "wtype": "word",
                                "ana": {
                                    "root": "ketika",
                                    "pos": "n|p",
                                    "form": "ketika"
                                }
                            }
                        ],
                        "syllables": 13
                    },
                    {
                        "line": "Harum berbau, semerbak belaka.",
                        "words": [
                            {
                                "wf": "Harum",
                                "wtype": "word",
                                "ana": {
                                    "root": "harum",
                                    "pos": "a",
                                    "form": "harum"
                                }
                            },
                            {
                                "wf": "berbau",
                                "wtype": "word",
                                "ana": {
                                    "root": "bau",
                                    "pos": "v",
                                    "form": "ber-bau"
                                }
                            },
                            {
                                "wf": ", ",
                                "wtype": "punct"
                            },
                            {
                                "wf": "semerbak",
                                "wtype": "word",
                                "ana": {
                                    "root": "semerbak",
                                    "pos": "a",
                                    "form": "semerbak"
                                }
                            },
                            {
                                "wf": "belaka",
                                "wtype": "word",
                                "ana": {
                                    "root": "belaka",
                                    "pos": "adv",
                                    "form": "belaka"
                                }
                            },
                            {
                                "wf": ".",
                                "wtype": "punct"
                            }
                        ],
                        "syllables": 10
                    },
                    {
                        "line": "Beta berahu bersuka raya",
                        "words": [
                            {
                                "wf": "Beta",
                                "wtype": "word",
                                "ana": {
                                    "root": "beta",
                                    "pos": "v",
                                    "form": "beta"
                                }
                            },
                            {
                                "wf": "berahu",
                                "wtype": "word",
                                "ana": {
                                    "root": "berahu",
                                    "pos": "v",
                                    "form": "berahu"
                                }
                            },
                            {
                                "wf": "bersuka",
                                "wtype": "word",
                                "ana": {
                                    "root": "bersuka",
                                    "pos": "v",
                                    "form": "bersuka"
                                }
                            },
                            {
                                "wf": "raya",
                                "wtype": "word",
                                "ana": {
                                    "root": "raya",
                                    "pos": "a",
                                    "form": "raya"
                                }
                            }
                        ],
                        "syllables": 10
                    },
                    {
                        "line": "Sekiranya bunga puspa mulia",
                        "words": [
                            {
                                "wf": "Sekiranya",
                                "wtype": "word",
                                "ana": {
                                    "root": "kira",
                                    "pos": "adv",
                                    "form": "sekira-nya"
                                }
                            },
                            {
                                "wf": "bunga",
                                "wtype": "word",
                                "ana": {
                                    "root": "bunga",
                                    "pos": "n",
                                    "form": "bunga"
                                }
                            },
                            {
                                "wf": "puspa",
                                "wtype": "word",
                                "ana": {
                                    "root": "puspa",
                                    "pos": "n",
                                    "form": "puspa"
                                }
                            },
                            {
                                "wf": "mulia",
                                "wtype": "word",
                                "ana": {
                                    "root": "mulia",
                                    "pos": "a",
                                    "form": "mulia"
                                }
                            }
                        ],
                        "syllables": 11
                    },
                    {
                        "line": "Dipetik handaiku, muda usia",
                        "words": [
                            {
                                "wf": "Dipetik",
                                "wtype": "word",
                                "ana": {
                                    "root": "Dipetik",
                                    "pos": "v",
                                    "form": "Dipetik"
                                }
                            },
                            {
                                "wf": "handaiku",
                                "wtype": "word",
                                "ana": {
                                    "root": "handai",
                                    "pos": "n",
                                    "form": "handai-ku"
                                }
                            },
                            {
                                "wf": ", ",
                                "wtype": "punct"
                            },
                            {
                                "wf": "muda",
                                "wtype": "word",
                                "ana": {
                                    "root": "muda",
                                    "pos": "a",
                                    "form": "muda"
                                }
                            },
                            {
                                "wf": "usia",
                                "wtype": "word",
                                "ana": {
                                    "root": "usia",
                                    "pos": "n",
                                    "form": "usia"
                                }
                            }
                        ],
                        "syllables": 11
                    },
                    {
                        "line": "Dijadikan karangan, nan permai kaya",
                        "words": [
                            {
                                "wf": "Dijadikan",
                                "wtype": "word",
                                "ana": {
                                    "root": "Dijadikan",
                                    "pos": "v",
                                    "form": "Dijadikan"
                                }
                            },
                            {
                                "wf": "karangan",
                                "wtype": "word",
                                "ana": {
                                    "root": "karang",
                                    "pos": "n",
                                    "form": "karang-an"
                                }
                            },
                            {
                                "wf": ", ",
                                "wtype": "punct"
                            },
                            {
                                "wf": "nan",
                                "wtype": "word",
                                "ana": {
                                    "root": "nan",
                                    "pos": "n",
                                    "form": "nan"
                                }
                            },
                            {
                                "wf": "permai",
                                "wtype": "word",
                                "ana": {
                                    "root": "permai",
                                    "pos": "a",
                                    "form": "permai"
                                }
                            },
                            {
                                "wf": "kaya",
                                "wtype": "word",
                                "ana": {
                                    "root": "kaya",
                                    "pos": "a",
                                    "form": "kaya"
                                }
                            }
                        ],
                        "syllables": 12
                    },
                    {
                        "line": "Semenjak kuntuman, kecil semula",
                        "words": [
                            {
                                "wf": "Semenjak",
                                "wtype": "word",
                                "ana": {
                                    "root": "semenjak",
                                    "pos": "p",
                                    "form": "semenjak"
                                }
                            },
                            {
                                "wf": "kuntuman",
                                "wtype": "word",
                                "ana": {
                                    "root": "kuntuman",
                                    "pos": "?",
                                    "form": "kuntuman"
                                }
                            },
                            {
                                "wf": ", ",
                                "wtype": "punct"
                            },
                            {
                                "wf": "kecil",
                                "wtype": "word",
                                "ana": {
                                    "root": "kecil",
                                    "pos": "a",
                                    "form": "kecil"
                                }
                            },
                            {
                                "wf": "semula",
                                "wtype": "word",
                                "ana": {
                                    "root": "mula",
                                    "pos": "n|adv",
                                    "form": "se-mula"
                                }
                            }
                        ],
                        "syllables": 11
                    },
                    {
                        "line": "Beta berniat membuat pahala,",
                        "words": [
                            {
                                "wf": "Beta",
                                "wtype": "word",
                                "ana": {
                                    "root": "beta",
                                    "pos": "v",
                                    "form": "beta"
                                }
                            },
                            {
                                "wf": "berniat",
                                "wtype": "word",
                                "ana": {
                                    "root": "niat",
                                    "pos": "v",
                                    "form": "ber-niat"
                                }
                            },
                            {
                                "wf": "membuat",
                                "wtype": "word",
                                "ana": {
                                    "root": "membuat",
                                    "pos": "v",
                                    "form": "membuat"
                                }
                            },
                            {
                                "wf": "pahala",
                                "wtype": "word",
                                "ana": {
                                    "root": "pahala",
                                    "pos": "n",
                                    "form": "pahala"
                                }
                            },
                            {
                                "wf": ",",
                                "wtype": "punct"
                            }
                        ],
                        "syllables": 11
                    },
                    {
                        "line": "Menjadikan perhiasan, atas kepala.",
                        "words": [
                            {
                                "wf": "Menjadikan",
                                "wtype": "word",
                                "ana": {
                                    "root": "jadi",
                                    "pos": "v",
                                    "form": "meN-jadi-kan"
                                }
                            },
                            {
                                "wf": "perhiasan",
                                "wtype": "word",
                                "ana": {
                                    "root": "hias",
                                    "pos": "n",
                                    "form": "per-hias-an"
                                }
                            },
                            {
                                "wf": ", ",
                                "wtype": "punct"
                            },
                            {
                                "wf": "atas",
                                "wtype": "word",
                                "ana": {
                                    "root": "atas",
                                    "pos": "n",
                                    "form": "atas"
                                }
                            },
                            {
                                "wf": "kepala",
                                "wtype": "word",
                                "ana": {
                                    "root": "kepala",
                                    "pos": "n",
                                    "form": "kepala"
                                }
                            },
                            {
                                "wf": ".",
                                "wtype": "punct"
                            }
                        ],
                        "syllables": 13
                    },
                    {
                        "line": "O  Cempaka, wangi baunya",
                        "words": [
                            {
                                "wf": "O",
                                "wtype": "word",
                                "ana": {
                                    "root": "o",
                                    "pos": "n",
                                    "form": "o"
                                }
                            },
                            {
                                "wf": "Cempaka",
                                "wtype": "word",
                                "ana": {
                                    "root": "cempaka",
                                    "pos": "n",
                                    "form": "cempaka"
                                }
                            },
                            {
                                "wf": ", ",
                                "wtype": "punct"
                            },
                            {
                                "wf": "wangi",
                                "wtype": "word",
                                "ana": {
                                    "root": "wangi",
                                    "pos": "a",
                                    "form": "wangi"
                                }
                            },
                            {
                                "wf": "baunya",
                                "wtype": "word",
                                "ana": {
                                    "root": "baunya",
                                    "pos": "n",
                                    "form": "baunya"
                                }
                            }
                        ],
                        "syllables": 7
                    },
                    {
                        "line": "Mari kupetik seberapa adanya",
                        "words": [
                            {
                                "wf": "Mari",
                                "wtype": "word",
                                "ana": {
                                    "root": "mari",
                                    "pos": "p",
                                    "form": "mari"
                                }
                            },
                            {
                                "wf": "kupetik",
                                "wtype": "word",
                                "ana": {
                                    "root": "petik",
                                    "pos": "v",
                                    "form": "ku-petik"
                                }
                            },
                            {
                                "wf": "seberapa",
                                "wtype": "word",
                                "ana": {
                                    "root": "beberapa",
                                    "pos": "num",
                                    "form": "seberapa"
                                }
                            },
                            {
                                "wf": "adanya",
                                "wtype": "word",
                                "ana": {
                                    "root": "ada",
                                    "pos": "n",
                                    "form": "ada-nya"
                                }
                            }
                        ],
                        "syllables": 12
                    },
                    {
                        "line": "Biar kugubah waktu la’i muda.",
                        "words": [
                            {
                                "wf": "Biar",
                                "wtype": "word",
                                "ana": {
                                    "root": "biar",
                                    "pos": "p",
                                    "form": "biar"
                                }
                            },
                            {
                                "wf": "kugubah",
                                "wtype": "word",
                                "ana": {
                                    "root": "gubah",
                                    "pos": "v",
                                    "form": "ku-gubah"
                                }
                            },
                            {
                                "wf": "waktu",
                                "wtype": "word",
                                "ana": {
                                    "root": "waktu",
                                    "pos": "n|p",
                                    "form": "waktu"
                                }
                            },
                            {
                                "wf": "la",
                                "wtype": "word",
                                "ana": {
                                    "root": "la",
                                    "pos": "n",
                                    "form": "la"
                                }
                            },
                            {
                                "wf": "’",
                                "wtype": "punct"
                            },
                            {
                                "wf": "i",
                                "wtype": "word",
                                "ana": {
                                    "root": "i",
                                    "pos": "v",
                                    "form": "i"
                                }
                            },
                            {
                                "wf": "muda",
                                "wtype": "word",
                                "ana": {
                                    "root": "muda",
                                    "pos": "a",
                                    "form": "muda"
                                }
                            },
                            {
                                "wf": ".",
                                "wtype": "punct"
                            }
                        ],
                        "syllables": 11
                    }
                ],
                "num_lines": 14
            }
        ]
    }
}