{
    "meta": {
        "file_name": "749.json",
        "id_bd": 749,
        "author": "Wing Kardjo Wangsaatmadja",
        "title": "Macbeth",
        "genre": "стихотворение",
        "year": "---",
        "num_lines": 14,
        "rhyme": "Есть",
        "syllables": [
            4,
            6,
            12,
            13,
            9,
            11,
            4,
            4,
            10,
            10,
            11,
            12,
            4,
            6
        ],
        "strofy": [
            14
        ]
    },
    "poem": {
        "text": "{Gagak hitam\r\nTerbang dalam kelam\r\nMestinya pada malam begini buta\r\nHantu-hantu menyiapkan kerja durjana\r\nTombak tajam menghujam korban\r\nMelepaskan setan-setan kurungan\r\nGagak hitam\r\nDalam malam\r\nPaginya beribu-ribu jiwa\r\nMerasa malapetaka tiba\r\nBeduk dipalu di segenap desa\r\nDerap kuda menderu di mana-mana\r\nGagak hitam\r\nTerbang dalam kelam}",
        "strof": [
            {
                "strof": "Gagak hitam\r\nTerbang dalam kelam\r\nMestinya pada malam begini buta\r\nHantu-hantu menyiapkan kerja durjana\r\nTombak tajam menghujam korban\r\nMelepaskan setan-setan kurungan\r\nGagak hitam\r\nDalam malam\r\nPaginya beribu-ribu jiwa\r\nMerasa malapetaka tiba\r\nBeduk dipalu di segenap desa\r\nDerap kuda menderu di mana-mana\r\nGagak hitam\r\nTerbang dalam kelam",
                "lines": [
                    {
                        "line": "Gagak hitam",
                        "words": [
                            {
                                "wf": "Gagak",
                                "wtype": "word",
                                "ana": {
                                    "root": "gagak",
                                    "pos": "n",
                                    "form": "gagak"
                                }
                            },
                            {
                                "wf": "hitam",
                                "wtype": "word",
                                "ana": {
                                    "root": "hitam",
                                    "pos": "n|a",
                                    "form": "hitam"
                                }
                            }
                        ],
                        "syllables": 4
                    },
                    {
                        "line": "Terbang dalam kelam",
                        "words": [
                            {
                                "wf": "Terbang",
                                "wtype": "word",
                                "ana": {
                                    "root": "terbang",
                                    "pos": "v",
                                    "form": "terbang"
                                }
                            },
                            {
                                "wf": "dalam",
                                "wtype": "word",
                                "ana": {
                                    "root": "dalam",
                                    "pos": "a|n",
                                    "form": "dalam"
                                }
                            },
                            {
                                "wf": "kelam",
                                "wtype": "word",
                                "ana": {
                                    "root": "kelam",
                                    "pos": "a",
                                    "form": "kelam"
                                }
                            }
                        ],
                        "syllables": 6
                    },
                    {
                        "line": "Mestinya pada malam begini buta",
                        "words": [
                            {
                                "wf": "Mestinya",
                                "wtype": "word",
                                "ana": {
                                    "root": "mesti",
                                    "pos": "adv",
                                    "form": "mesti-nya"
                                }
                            },
                            {
                                "wf": "pada",
                                "wtype": "word",
                                "ana": {
                                    "root": "pada",
                                    "pos": "p",
                                    "form": "pada"
                                }
                            },
                            {
                                "wf": "malam",
                                "wtype": "word",
                                "ana": {
                                    "root": "malam",
                                    "pos": "n",
                                    "form": "malam"
                                }
                            },
                            {
                                "wf": "begini",
                                "wtype": "word",
                                "ana": {
                                    "root": "begini",
                                    "pos": "pron",
                                    "form": "begini"
                                }
                            },
                            {
                                "wf": "buta",
                                "wtype": "word",
                                "ana": {
                                    "root": "buta",
                                    "pos": "a",
                                    "form": "buta"
                                }
                            }
                        ],
                        "syllables": 12
                    },
                    {
                        "line": "Hantu-hantu menyiapkan kerja durjana",
                        "words": [
                            {
                                "wf": "Hantu-hantu",
                                "wtype": "word",
                                "ana": {
                                    "root": "hantu",
                                    "pos": "n",
                                    "form": "hantu-hantu"
                                }
                            },
                            {
                                "wf": "menyiapkan",
                                "wtype": "word",
                                "ana": {
                                    "root": "siap",
                                    "pos": "v",
                                    "form": "meN-siap-kan"
                                }
                            },
                            {
                                "wf": "kerja",
                                "wtype": "word",
                                "ana": {
                                    "root": "kerja",
                                    "pos": "n|v",
                                    "form": "kerja"
                                }
                            },
                            {
                                "wf": "durjana",
                                "wtype": "word",
                                "ana": {
                                    "root": "durjana",
                                    "pos": "a|n",
                                    "form": "durjana"
                                }
                            }
                        ],
                        "syllables": 13
                    },
                    {
                        "line": "Tombak tajam menghujam korban",
                        "words": [
                            {
                                "wf": "Tombak",
                                "wtype": "word",
                                "ana": {
                                    "root": "tombak",
                                    "pos": "n",
                                    "form": "tombak"
                                }
                            },
                            {
                                "wf": "tajam",
                                "wtype": "word",
                                "ana": {
                                    "root": "tajam",
                                    "pos": "a",
                                    "form": "tajam"
                                }
                            },
                            {
                                "wf": "menghujam",
                                "wtype": "word",
                                "ana": {
                                    "root": "menghujam",
                                    "pos": "v",
                                    "form": "menghujam"
                                }
                            },
                            {
                                "wf": "korban",
                                "wtype": "word",
                                "ana": {
                                    "root": "korban",
                                    "pos": "n",
                                    "form": "korban"
                                }
                            }
                        ],
                        "syllables": 9
                    },
                    {
                        "line": "Melepaskan setan-setan kurungan",
                        "words": [
                            {
                                "wf": "Melepaskan",
                                "wtype": "word",
                                "ana": {
                                    "root": "lepas",
                                    "pos": "v",
                                    "form": "meN-lepas-kan"
                                }
                            },
                            {
                                "wf": "setan-setan",
                                "wtype": "word",
                                "ana": {
                                    "root": "setan",
                                    "pos": "",
                                    "form": "setan-setan"
                                }
                            },
                            {
                                "wf": "kurungan",
                                "wtype": "word",
                                "ana": {
                                    "root": "kurung",
                                    "pos": "n",
                                    "form": "kurung-an"
                                }
                            }
                        ],
                        "syllables": 11
                    },
                    {
                        "line": "Gagak hitam",
                        "words": [
                            {
                                "wf": "Gagak",
                                "wtype": "word",
                                "ana": {
                                    "root": "gagak",
                                    "pos": "n",
                                    "form": "gagak"
                                }
                            },
                            {
                                "wf": "hitam",
                                "wtype": "word",
                                "ana": {
                                    "root": "hitam",
                                    "pos": "n|a",
                                    "form": "hitam"
                                }
                            }
                        ],
                        "syllables": 4
                    },
                    {
                        "line": "Dalam malam",
                        "words": [
                            {
                                "wf": "Dalam",
                                "wtype": "word",
                                "ana": {
                                    "root": "dalam",
                                    "pos": "a|n",
                                    "form": "dalam"
                                }
                            },
                            {
                                "wf": "malam",
                                "wtype": "word",
                                "ana": {
                                    "root": "malam",
                                    "pos": "n",
                                    "form": "malam"
                                }
                            }
                        ],
                        "syllables": 4
                    },
                    {
                        "line": "Paginya beribu-ribu jiwa",
                        "words": [
                            {
                                "wf": "Paginya",
                                "wtype": "word",
                                "ana": {
                                    "root": "pagi",
                                    "pos": "n",
                                    "form": "pagi-nya"
                                }
                            },
                            {
                                "wf": "beribu-ribu",
                                "wtype": "word",
                                "ana": {
                                    "root": "ribu",
                                    "pos": "num",
                                    "form": "ber-ribu-ribu"
                                }
                            },
                            {
                                "wf": "jiwa",
                                "wtype": "word",
                                "ana": {
                                    "root": "jiwa",
                                    "pos": "n",
                                    "form": "jiwa"
                                }
                            }
                        ],
                        "syllables": 10
                    },
                    {
                        "line": "Merasa malapetaka tiba",
                        "words": [
                            {
                                "wf": "Merasa",
                                "wtype": "word",
                                "ana": {
                                    "root": "rasa",
                                    "pos": "v",
                                    "form": "meN-rasa"
                                }
                            },
                            {
                                "wf": "malapetaka",
                                "wtype": "word",
                                "ana": {
                                    "root": "malapetaka",
                                    "pos": "n",
                                    "form": "malapetaka"
                                }
                            },
                            {
                                "wf": "tiba",
                                "wtype": "word",
                                "ana": {
                                    "root": "tiba",
                                    "pos": "v",
                                    "form": "tiba"
                                }
                            }
                        ],
                        "syllables": 10
                    },
                    {
                        "line": "Beduk dipalu di segenap desa",
                        "words": [
                            {
                                "wf": "Beduk",
                                "wtype": "word",
                                "ana": {
                                    "root": "beduk",
                                    "pos": "n",
                                    "form": "beduk"
                                }
                            },
                            {
                                "wf": "dipalu",
                                "wtype": "word",
                                "ana": {
                                    "root": "palu",
                                    "pos": "n",
                                    "form": "di-palu"
                                }
                            },
                            {
                                "wf": "di",
                                "wtype": "word",
                                "ana": {
                                    "root": "di",
                                    "pos": "p",
                                    "form": "di"
                                }
                            },
                            {
                                "wf": "segenap",
                                "wtype": "word",
                                "ana": {
                                    "root": "genap",
                                    "pos": "num",
                                    "form": "se-genap"
                                }
                            },
                            {
                                "wf": "desa",
                                "wtype": "word",
                                "ana": {
                                    "root": "desa",
                                    "pos": "",
                                    "form": "desa"
                                }
                            }
                        ],
                        "syllables": 11
                    },
                    {
                        "line": "Derap kuda menderu di mana-mana",
                        "words": [
                            {
                                "wf": "Derap",
                                "wtype": "word",
                                "ana": {
                                    "root": "derap",
                                    "pos": "n",
                                    "form": "derap"
                                }
                            },
                            {
                                "wf": "kuda",
                                "wtype": "word",
                                "ana": {
                                    "root": "kuda",
                                    "pos": "n",
                                    "form": "kuda"
                                }
                            },
                            {
                                "wf": "menderu",
                                "wtype": "word",
                                "ana": {
                                    "root": "deru",
                                    "pos": "v",
                                    "form": "meN-deru"
                                }
                            },
                            {
                                "wf": "di",
                                "wtype": "word",
                                "ana": {
                                    "root": "di",
                                    "pos": "p",
                                    "form": "di"
                                }
                            },
                            {
                                "wf": "mana-mana",
                                "wtype": "word",
                                "ana": {
                                    "root": "mana",
                                    "pos": "pron",
                                    "form": "mana-mana"
                                }
                            }
                        ],
                        "syllables": 12
                    },
                    {
                        "line": "Gagak hitam",
                        "words": [
                            {
                                "wf": "Gagak",
                                "wtype": "word",
                                "ana": {
                                    "root": "gagak",
                                    "pos": "n",
                                    "form": "gagak"
                                }
                            },
                            {
                                "wf": "hitam",
                                "wtype": "word",
                                "ana": {
                                    "root": "hitam",
                                    "pos": "n|a",
                                    "form": "hitam"
                                }
                            }
                        ],
                        "syllables": 4
                    },
                    {
                        "line": "Terbang dalam kelam",
                        "words": [
                            {
                                "wf": "Terbang",
                                "wtype": "word",
                                "ana": {
                                    "root": "terbang",
                                    "pos": "v",
                                    "form": "terbang"
                                }
                            },
                            {
                                "wf": "dalam",
                                "wtype": "word",
                                "ana": {
                                    "root": "dalam",
                                    "pos": "a|n",
                                    "form": "dalam"
                                }
                            },
                            {
                                "wf": "kelam",
                                "wtype": "word",
                                "ana": {
                                    "root": "kelam",
                                    "pos": "a",
                                    "form": "kelam"
                                }
                            }
                        ],
                        "syllables": 6
                    }
                ],
                "num_lines": 14
            }
        ]
    }
}